emoji_lang/__init__.py
emoji_lang/cli.py
emoji_lang/interpreter.py
emoji_lang/lexer.py
emoji_lang/parser_ast.py
emoji_lang-0.1.dist-info/METADATA
emoji_lang-0.1.dist-info/WHEEL
emoji_lang-0.1.dist-info/entry_points.txt
emoji_lang-0.1.dist-info/top_level.txt
emoji_lang-0.1.dist-info/RECORD
